{"title":"Nordland","summary":{"dager_q25":3,"dager_median":29,"dager_q75":105.95833333333333,"dager_maks":605.9583333333334,"emner":[{"emne":233,"d":3598,"k":2205,"m":1393,"d1":24,"d2":68,"d3":219,"d4":376,"d5":883,"d6":2028},{"emne":306,"d":351,"k":219,"m":132,"d1":51,"d2":110,"d3":26,"d4":28,"d5":38,"d6":98},{"emne":209,"d":22,"k":22,"m":0,"d1":0,"d2":0,"d3":0,"d4":1,"d5":3,"d6":18},{"emne":599,"d":515,"k":199,"m":316,"d1":204,"d2":45,"d3":69,"d4":87,"d5":74,"d6":36},{"emne":1020,"d":88,"k":42,"m":46,"d1":20,"d2":11,"d3":7,"d4":8,"d5":16,"d6":26},{"emne":704,"d":441,"k":290,"m":151,"d1":1,"d2":58,"d3":59,"d4":86,"d5":124,"d6":113},{"emne":720,"d":52,"k":34,"m":18,"d1":47,"d2":0,"d3":3,"d4":1,"d5":1,"d6":0},{"emne":501,"d":405,"k":312,"m":93,"d1":2,"d2":10,"d3":11,"d4":37,"d5":96,"d6":249},{"emne":702,"d":1888,"k":1531,"m":357,"d1":14,"d2":36,"d3":63,"d4":104,"d5":343,"d6":1328},{"emne":299,"d":524,"k":378,"m":146,"d1":4,"d2":17,"d3":32,"d4":38,"d5":98,"d6":335},{"emne":298,"d":138,"k":122,"m":16,"d1":0,"d2":4,"d3":0,"d4":1,"d5":33,"d6":100},{"emne":706,"d":832,"k":528,"m":304,"d1":14,"d2":49,"d3":90,"d4":77,"d5":81,"d6":521},{"emne":210,"d":849,"k":843,"m":6,"d1":14,"d2":11,"d3":45,"d4":68,"d5":167,"d6":544},{"emne":503,"d":134,"k":97,"m":37,"d1":14,"d2":19,"d3":10,"d4":10,"d5":36,"d6":45},{"emne":403,"d":92,"k":76,"m":16,"d1":0,"d2":0,"d3":4,"d4":7,"d5":24,"d6":57},{"emne":211,"d":136,"k":38,"m":98,"d1":0,"d2":3,"d3":1,"d4":6,"d5":7,"d6":119},{"emne":701,"d":203,"k":175,"m":28,"d1":0,"d2":5,"d3":7,"d4":19,"d5":52,"d6":120},{"emne":406,"d":22,"k":21,"m":1,"d1":0,"d2":1,"d3":1,"d4":3,"d5":6,"d6":11},{"emne":799,"d":14,"k":11,"m":3,"d1":0,"d2":0,"d3":1,"d4":2,"d5":2,"d6":9},{"emne":301,"d":197,"k":158,"m":39,"d1":0,"d2":0,"d3":3,"d4":2,"d5":21,"d6":171},{"emne":602,"d":4,"k":4,"m":0,"d1":0,"d2":0,"d3":0,"d4":0,"d5":2,"d6":2},{"emne":407,"d":11,"k":6,"m":5,"d1":0,"d2":0,"d3":1,"d4":2,"d5":2,"d6":6},{"emne":101,"d":20,"k":14,"m":6,"d1":20,"d2":0,"d3":0,"d4":0,"d5":0,"d6":0},{"emne":108,"d":14,"k":9,"m":5,"d1":0,"d2":0,"d3":1,"d4":5,"d5":4,"d6":4},{"emne":611,"d":11,"k":4,"m":7,"d1":0,"d2":0,"d3":0,"d4":0,"d5":0,"d6":11},{"emne":219,"d":60,"k":60,"m":0,"d1":0,"d2":3,"d3":1,"d4":6,"d5":8,"d6":42},{"emne":212,"d":9,"k":1,"m":8,"d1":1,"d2":1,"d3":1,"d4":0,"d5":1,"d6":5},{"emne":206,"d":638,"k":491,"m":147,"d1":17,"d2":12,"d3":0,"d4":8,"d5":19,"d6":582},{"emne":230,"d":715,"k":371,"m":344,"d1":95,"d2":71,"d3":39,"d4":104,"d5":149,"d6":257},{"emne":205,"d":43,"k":28,"m":15,"d1":29,"d2":4,"d3":3,"d4":2,"d5":3,"d6":2},{"emne":408,"d":8,"k":3,"m":5,"d1":0,"d2":0,"d3":0,"d4":0,"d5":0,"d6":8},{"emne":499,"d":12,"k":6,"m":6,"d1":0,"d2":1,"d3":2,"d4":1,"d5":2,"d6":6},{"emne":1006,"d":14,"k":4,"m":10,"d1":0,"d2":0,"d3":6,"d4":2,"d5":5,"d6":1},{"emne":909,"d":20,"k":12,"m":8,"d1":0,"d2":18,"d3":2,"d4":0,"d5":0,"d6":0},{"emne":398,"d":577,"k":272,"m":305,"d1":577,"d2":0,"d3":0,"d4":0,"d5":0,"d6":0},{"emne":508,"d":1114,"k":665,"m":449,"d1":465,"d2":88,"d3":259,"d4":212,"d5":73,"d6":17},{"emne":234,"d":16,"k":2,"m":14,"d1":0,"d2":0,"d3":0,"d4":0,"d5":2,"d6":14},{"emne":506,"d":926,"k":458,"m":468,"d1":0,"d2":73,"d3":161,"d4":190,"d5":187,"d6":315},{"emne":1005,"d":692,"k":215,"m":477,"d1":215,"d2":187,"d3":137,"d4":68,"d5":63,"d6":22},{"emne":1004,"d":292,"k":240,"m":52,"d1":1,"d2":45,"d3":63,"d4":64,"d5":71,"d6":48},{"emne":1001,"d":72,"k":22,"m":50,"d1":0,"d2":5,"d3":23,"d4":9,"d5":11,"d6":24},{"emne":1099,"d":35,"k":32,"m":3,"d1":1,"d2":2,"d3":6,"d4":6,"d5":10,"d6":10},{"emne":1003,"d":19,"k":14,"m":5,"d1":1,"d2":3,"d3":6,"d4":5,"d5":4,"d6":0}],"korte_kurs":[{"emne":508,"kurs":88},{"emne":706,"kurs":85},{"emne":704,"kurs":57},{"emne":599,"kurs":55},{"emne":702,"kurs":53},{"emne":506,"kurs":51},{"emne":299,"kurs":47},{"emne":1004,"kurs":32},{"emne":501,"kurs":28},{"emne":210,"kurs":27},{"emne":230,"kurs":27},{"emne":701,"kurs":15},{"emne":1005,"kurs":14},{"emne":301,"kurs":11},{"emne":503,"kurs":10},{"emne":1020,"kurs":8},{"emne":720,"kurs":8},{"emne":206,"kurs":7},{"emne":298,"kurs":6},{"emne":398,"kurs":6},{"emne":799,"kurs":4},{"emne":1099,"kurs":4},{"emne":209,"kurs":3},{"emne":211,"kurs":3},{"emne":1001,"kurs":3},{"emne":403,"kurs":2},{"emne":406,"kurs":2},{"emne":219,"kurs":2},{"emne":205,"kurs":2},{"emne":1006,"kurs":2},{"emne":233,"kurs":1},{"emne":306,"kurs":1},{"emne":602,"kurs":1},{"emne":101,"kurs":1},{"emne":212,"kurs":1},{"emne":909,"kurs":1},{"emne":1003,"kurs":1}],"lange_kurs":[{"emne":233,"kurs":209},{"emne":702,"kurs":185},{"emne":506,"kurs":116},{"emne":210,"kurs":112},{"emne":706,"kurs":75},{"emne":206,"kurs":51},{"emne":306,"kurs":49},{"emne":230,"kurs":48},{"emne":299,"kurs":38},{"emne":1005,"kurs":38},{"emne":398,"kurs":37},{"emne":704,"kurs":32},{"emne":211,"kurs":25},{"emne":298,"kurs":18},{"emne":501,"kurs":14},{"emne":508,"kurs":13},{"emne":1004,"kurs":11},{"emne":503,"kurs":8},{"emne":1001,"kurs":7},{"emne":599,"kurs":5},{"emne":1020,"kurs":5},{"emne":403,"kurs":5},{"emne":219,"kurs":5},{"emne":205,"kurs":5},{"emne":701,"kurs":3},{"emne":499,"kurs":3},{"emne":407,"kurs":2},{"emne":611,"kurs":2},{"emne":234,"kurs":2},{"emne":209,"kurs":1},{"emne":799,"kurs":1},{"emne":301,"kurs":1},{"emne":108,"kurs":1},{"emne":408,"kurs":1},{"emne":1099,"kurs":1}],"organisasjoner":[{"sf":2508,"org":32,"kurs":188,"timer":3209.5,"delt":1618},{"sf":2510,"org":1,"kurs":183,"timer":5188,"delt":1150},{"sf":2525,"org":206,"kurs":173,"timer":8934,"delt":3038},{"sf":2508,"org":20,"kurs":157,"timer":6436,"delt":735},{"sf":2508,"org":10,"kurs":129,"timer":3720,"delt":923},{"sf":2535,"org":1,"kurs":91,"timer":1505,"delt":576},{"sf":2539,"org":25,"kurs":85,"timer":2696,"delt":387},{"sf":2542,"org":1,"kurs":75,"timer":699,"delt":344},{"sf":2508,"org":37,"kurs":57,"timer":769,"delt":396},{"sf":2539,"org":1,"kurs":55,"timer":1451,"delt":718},{"sf":2521,"org":26,"kurs":54,"timer":583,"delt":549},{"sf":2504,"org":53,"kurs":46,"timer":634,"delt":314},{"sf":2510,"org":27,"kurs":46,"timer":1627.5,"delt":516},{"sf":2510,"org":45,"kurs":43,"timer":810.5,"delt":577},{"sf":2539,"org":2,"kurs":43,"timer":642.5,"delt":291},{"sf":2521,"org":null,"kurs":29,"timer":238,"delt":276},{"sf":2525,"org":421,"kurs":26,"timer":1133,"delt":216},{"sf":2510,"org":2,"kurs":25,"timer":577.5,"delt":184},{"sf":2508,"org":23,"kurs":20,"timer":314.5,"delt":116},{"sf":2510,"org":4,"kurs":18,"timer":850,"delt":108},{"sf":2504,"org":1,"kurs":17,"timer":451.5,"delt":97},{"sf":2521,"org":33,"kurs":16,"timer":113,"delt":174},{"sf":2525,"org":411,"kurs":16,"timer":152.5,"delt":133},{"sf":2508,"org":9,"kurs":15,"timer":181,"delt":199},{"sf":2525,"org":201,"kurs":15,"timer":784.5,"delt":285},{"sf":2525,"org":511,"kurs":13,"timer":680.5,"delt":160},{"sf":2525,"org":301,"kurs":11,"timer":357.5,"delt":125},{"sf":2521,"org":30,"kurs":9,"timer":152,"delt":121},{"sf":2504,"org":4,"kurs":7,"timer":84,"delt":47},{"sf":2521,"org":45,"kurs":7,"timer":89,"delt":79},{"sf":2508,"org":33,"kurs":6,"timer":25,"delt":65},{"sf":2525,"org":202,"kurs":6,"timer":268.5,"delt":128},{"sf":2525,"org":601,"kurs":6,"timer":230,"delt":48},{"sf":2539,"org":26,"kurs":6,"timer":59,"delt":40},{"sf":2504,"org":45,"kurs":5,"timer":65,"delt":85},{"sf":2508,"org":42,"kurs":5,"timer":221,"delt":35},{"sf":2539,"org":4,"kurs":5,"timer":196,"delt":32},{"sf":2539,"org":8,"kurs":5,"timer":55,"delt":35},{"sf":2504,"org":15,"kurs":4,"timer":111,"delt":47},{"sf":2508,"org":40,"kurs":4,"timer":62,"delt":18},{"sf":2525,"org":212,"kurs":4,"timer":102,"delt":73},{"sf":2525,"org":401,"kurs":4,"timer":139.5,"delt":80},{"sf":2539,"org":5,"kurs":4,"timer":55,"delt":32},{"sf":2504,"org":44,"kurs":3,"timer":120,"delt":14},{"sf":2504,"org":49,"kurs":3,"timer":63,"delt":19},{"sf":2508,"org":100,"kurs":3,"timer":42,"delt":50},{"sf":2510,"org":3,"kurs":3,"timer":220,"delt":23},{"sf":2510,"org":42,"kurs":3,"timer":24,"delt":25},{"sf":2521,"org":43,"kurs":3,"timer":54,"delt":18},{"sf":2504,"org":3,"kurs":2,"timer":132.5,"delt":23},{"sf":2504,"org":13,"kurs":2,"timer":56,"delt":12},{"sf":2508,"org":1,"kurs":2,"timer":10,"delt":16},{"sf":2508,"org":14,"kurs":2,"timer":32,"delt":14},{"sf":2508,"org":53,"kurs":2,"timer":18,"delt":19},{"sf":2508,"org":8,"kurs":2,"timer":35,"delt":17},{"sf":2510,"org":16,"kurs":2,"timer":54,"delt":10},{"sf":2521,"org":55,"kurs":2,"timer":8,"delt":20},{"sf":2521,"org":48,"kurs":2,"timer":28,"delt":39},{"sf":2521,"org":23,"kurs":2,"timer":10,"delt":26},{"sf":2521,"org":27,"kurs":2,"timer":16,"delt":18},{"sf":2521,"org":31,"kurs":2,"timer":8,"delt":17},{"sf":2521,"org":38,"kurs":2,"timer":52,"delt":8},{"sf":2539,"org":3,"kurs":2,"timer":24,"delt":28},{"sf":2504,"org":61,"kurs":1,"timer":229,"delt":9},{"sf":2508,"org":19,"kurs":1,"timer":11,"delt":6},{"sf":2508,"org":null,"kurs":1,"timer":11,"delt":6},{"sf":2508,"org":28,"kurs":1,"timer":12,"delt":56},{"sf":2508,"org":34,"kurs":1,"timer":6,"delt":8},{"sf":2508,"org":5,"kurs":1,"timer":28,"delt":20},{"sf":2510,"org":26,"kurs":1,"timer":36,"delt":20},{"sf":2510,"org":32,"kurs":1,"timer":123,"delt":8},{"sf":2521,"org":12,"kurs":1,"timer":34,"delt":4},{"sf":2521,"org":49,"kurs":1,"timer":8,"delt":13},{"sf":2521,"org":13,"kurs":1,"timer":4,"delt":8},{"sf":2521,"org":59,"kurs":1,"timer":13,"delt":5},{"sf":2521,"org":19,"kurs":1,"timer":4,"delt":10},{"sf":2521,"org":29,"kurs":1,"timer":13,"delt":11},{"sf":2521,"org":32,"kurs":1,"timer":4,"delt":4},{"sf":2521,"org":56,"kurs":1,"timer":10,"delt":17},{"sf":2525,"org":503,"kurs":1,"timer":6,"delt":7},{"sf":2535,"org":2,"kurs":1,"timer":10,"delt":6},{"sf":2539,"org":27,"kurs":1,"timer":15,"delt":19}],"kommuner":[{"kom":1804,"kurs":367,"pop":53259,"navn":"Bodø","delt":3784},{"kom":1806,"kurs":171,"pop":21515,"navn":"Narvik","delt":1408},{"kom":1853,"kurs":156,"pop":1310,"navn":"Evenes - Evenášši","delt":738},{"kom":1833,"kurs":137,"pop":25980,"navn":"Rana","delt":1314},{"kom":1824,"kurs":89,"pop":13342,"navn":"Vefsn","delt":880},{"kom":1813,"kurs":74,"pop":7787,"navn":"Brønnøy","delt":600},{"kom":1867,"kurs":74,"pop":2584,"navn":"Bø","delt":472},{"kom":1841,"kurs":64,"pop":9572,"navn":"Fauske - Fuossko","delt":556},{"kom":1870,"kurs":61,"pop":10561,"navn":"Sortland - Suortá","delt":635},{"kom":1868,"kurs":60,"pop":4533,"navn":"Øksnes","delt":450},{"kom":1820,"kurs":58,"pop":7300,"navn":"Alstahaug","delt":719},{"kom":1866,"kurs":57,"pop":8184,"navn":"Hadsel","delt":492},{"kom":1860,"kurs":54,"pop":11551,"navn":"Vestvågøy","delt":520},{"kom":1812,"kurs":41,"pop":1970,"navn":"Sømna","delt":334},{"kom":1871,"kurs":34,"pop":4577,"navn":"Andøy","delt":275},{"kom":1837,"kurs":32,"pop":6212,"navn":"Meløy","delt":264},{"kom":1840,"kurs":31,"pop":4650,"navn":"Saltdal","delt":355},{"kom":1822,"kurs":28,"pop":2270,"navn":"Leirfjord","delt":188},{"kom":1865,"kurs":24,"pop":9736,"navn":"Vågan","delt":195},{"kom":1832,"kurs":22,"pop":4459,"navn":"Hemnes","delt":265},{"kom":1848,"kurs":21,"pop":2665,"navn":"Steigen","delt":195},{"kom":1834,"kurs":19,"pop":1852,"navn":"Lurøy","delt":157},{"kom":1839,"kurs":14,"pop":1027,"navn":"Beiarn","delt":113},{"kom":1875,"kurs":13,"pop":2682,"navn":"Hábmer - Hamarøy","delt":98},{"kom":1828,"kurs":13,"pop":1783,"navn":"Nesna","delt":117},{"kom":1815,"kurs":12,"pop":1219,"navn":"Vega","delt":144},{"kom":1838,"kurs":12,"pop":1928,"navn":"Gildeskål","delt":65},{"kom":1851,"kurs":12,"pop":1985,"navn":"Lødingen","delt":79},{"kom":1825,"kurs":8,"pop":1454,"navn":"Grane","delt":80},{"kom":1826,"kurs":7,"pop":1278,"navn":"Aarborte - Hattfjelldal","delt":38},{"kom":1845,"kurs":6,"pop":1845,"navn":"Sørfold","delt":92},{"kom":1811,"kurs":6,"pop":1391,"navn":"Bindal","delt":41},{"kom":1835,"kurs":6,"pop":444,"navn":"Træna","delt":28},{"kom":1859,"kurs":4,"pop":1220,"navn":"Flakstad","delt":28},{"kom":1816,"kurs":3,"pop":454,"navn":"Vevelstad","delt":29},{"kom":1874,"kurs":2,"pop":979,"navn":"Moskenes","delt":22},{"kom":1827,"kurs":2,"pop":1391,"navn":"Dønna","delt":11},{"kom":1836,"kurs":2,"pop":1139,"navn":"Rødøy","delt":17},{"kom":1856,"kurs":2,"pop":469,"navn":"Røst","delt":25}],"kommunerAll":41,"kommunerMissing":[{"navn":"Herøy (Nordland)"},{"navn":"Værøy"}],"fylker":[{"fylke":18,"kurs":1798,"pop":241084,"navn":"Nordland - Nordlánnda","delt":15823}],"studieforbund":[{"sf":2508,"kurs":597,"timer":15143,"delt":4317},{"sf":2525,"kurs":275,"timer":12788,"delt":4293},{"sf":2510,"kurs":325,"timer":9510.5,"delt":2621},{"sf":2539,"kurs":206,"timer":5193.5,"delt":1582},{"sf":2504,"kurs":90,"timer":1946,"delt":667},{"sf":2535,"kurs":92,"timer":1515,"delt":582},{"sf":2521,"kurs":138,"timer":1441,"delt":1417},{"sf":2542,"kurs":75,"timer":699,"delt":344}],"kurs_bin":[{"label":"1 dag","kurs":230},{"label":"2-7 dager","kurs":439},{"label":"8-30 dager","kurs":234},{"label":"1-3 måneder","kurs":341},{"label":"3-6 måneder","kurs":504},{"label":"Over 6 måneder","kurs":50}]},"history":[{"korte_kurs":669,"lange_kurs":1129,"aar":2023,"kurs":1798,"timer":48236,"timer_median":20,"deltakere":15823,"deltakere_median":6,"deltakere_kvinner":10234,"deltakere_menn":5589,"deltakere_10":1831,"deltakere_20":960,"deltakere_30":1362,"deltakere_40":1645,"deltakere_50":2721,"deltakere_60":7304,"organisasjoner":82},{"korte_kurs":592,"lange_kurs":1089,"aar":2022,"kurs":1681,"timer":45647,"timer_median":21,"deltakere":14247,"deltakere_median":6,"deltakere_kvinner":8946,"deltakere_menn":5301,"deltakere_10":1525,"deltakere_20":949,"deltakere_30":1109,"deltakere_40":1461,"deltakere_50":2486,"deltakere_60":6717,"organisasjoner":76}],"histogram":[{"2022":172,"2023":88,"label":"0-3"},{"2022":830,"2023":973,"label":"4-7"},{"2022":280,"2023":314,"label":"8-11"},{"2022":190,"2023":183,"label":"12-15"},{"2022":91,"2023":110,"label":"16-19"},{"2022":58,"2023":49,"label":"20-23"},{"2022":31,"2023":27,"label":"24-27"},{"2022":15,"2023":26,"label":"28-31"},{"2022":5,"2023":15,"label":"32-35"},{"2022":5,"2023":4,"label":"40+"}]}